[{
    "date": 1480851888994,
    "sender": "Laura Blanco Antón",
    "tittle": "yeahhh",
    "content": "nothing to say",
    "media": []
}, {
    "date": 1461851888994,
    "sender": "María Gonzalez Aznar",
    "tittle": "alojaaa",
    "content": "nothing to say",
    "media": []
}, {
    "date": 1431851888994,
    "sender": "Pedro Manrique Guzmán",
    "tittle": "hola",
    "content": "nothing to say",
    "media": []
}, {
    "date": 1451851888994,
    "sender": "Jose Moreno Díaz",
    "tittle": "hi",
    "content": "nothing to say",
    "media": []
}]